dumb_menu/__init__.py
lw_menu-1.0.5.dist-info/METADATA
lw_menu-1.0.5.dist-info/WHEEL
lw_menu-1.0.5.dist-info/top_level.txt
lw_menu-1.0.5.dist-info/RECORD
