Metadata-Version: 2.1
Name: lw-menu
Version: 1.0.5
Summary: A short description of your package
Author: lw
Author-email: 2976638734@qq.com
Classifier: Programming Language :: Python :: 3
Classifier: License :: OSI Approved :: MIT License
Classifier: Operating System :: OS Independent
Requires-Python: >=3.6
